django_bootstrap_email/__init__.py
django_bootstrap_email/apps.py
django_bootstrap_email/templatetags/__init__.py
django_bootstrap_email/templatetags/bootstrap_email.py
django_bs_email-0.2.1.dist-info/LICENSE
django_bs_email-0.2.1.dist-info/METADATA
django_bs_email-0.2.1.dist-info/WHEEL
django_bs_email-0.2.1.dist-info/top_level.txt
django_bs_email-0.2.1.dist-info/RECORD
