Metadata-Version: 2.1
Name: django-bs-email
Version: 0.2.1
Summary: Django application with Bootstrap email template tag.
Author: Jeremy Thompson
License: MIT License
Project-URL: Homepage, https://github.com/jhthompson/django-bootstrap-email
Project-URL: Changelog, https://github.com/jhthompson/django-bootstrap-email/releases
Project-URL: Issues, https://github.com/jhthompson/django-bootstrap-email/issues
Project-URL: CI, https://github.com/jhthompson/django-bootstrap-email/actions
Requires-Python: >=3.9
License-File: LICENSE
Requires-Dist: bootstrap-email
Requires-Dist: Django
